COPYING
ChangeLog
INSTALL
MANIFEST.in
README
setup.py
AREM/Constants.py
AREM/OptValidator.py
AREM/OutputWriter.py
AREM/PeakDetect.py
AREM/PeakModel.py
AREM/Prob.py
AREM/__init__.py
AREM/ipdb.py
AREM.egg-info/PKG-INFO
AREM.egg-info/SOURCES.txt
AREM.egg-info/dependency_links.txt
AREM.egg-info/top_level.txt
AREM/IO/FeatIO.py
AREM/IO/Parser.py
AREM/IO/__init__.py
bin/arem
bin/elandexport2bed
bin/elandmulti2bed
bin/elandresult2bed
bin/sam2bed
bin/wignorm