Metadata-Version: 1.0
Name: AREM
Version: 1.0.1
Summary: Aligning Reads by Expectation-Maximization.
Home-page: http://cbcl.ics.uci.edu/AREM
Author: Jake Biesinger; Daniel Newkirk; Alvin Chon; Yong Zhang; Tao (Foo) Liu
Author-email: jake.biesinger@gmail.com; dnewkirk@uci.edu; achon@uci.edu; zy@jimmy.harvard.edu; taoliu@jimmy.harvard.edu
License: Creative
Platform: UNKNOWN
Classifier: Development Status :: 4 - Beta
Classifier: Environment :: Console
Classifier: Intended Audience :: Developers
Classifier: Intended Audience :: Science/Research
Classifier: License :: OSI Approved :: Artistic License
Classifier: Operating System :: MacOS :: MacOS X
Classifier: Operating System :: Microsoft :: Windows
Classifier: Operating System :: POSIX
Classifier: Programming Language :: Python :: 2.6
Classifier: Programming Language :: Python :: 2.7
Classifier: Topic :: Scientific/Engineering :: Bio-Informatics
